data/data_utils.py
data/Synthetic/synthetic_signal.py
docs/conf.py
experiments/benchmark_experiment.py
results/results_utils.py
tsmd/__init__.py
tsmd/competitors/adaptative_persistence.py
tsmd/competitors/grammarviz.py
tsmd/competitors/latentmotifs.py
tsmd/competitors/locomotif.py
tsmd/competitors/matrixprofile.py
tsmd/competitors/mdl.py
tsmd/competitors/motiflets.py
tsmd/competitors/motiflets_numba.py
tsmd/competitors/panmatrixprofile.py
tsmd/competitors/persistence.py
tsmd/competitors/setfinder.py
tsmd/competitors/valmod.py
tsmd/competitors/competitors_tools/locomotif_original_tools.py
tsmd/competitors/competitors_tools/motiflets_distances.py
tsmd/competitors/competitors_tools/motiflets_tools.py
tsmd/competitors/competitors_tools/motiflets_w_numba_tools.py
tsmd/competitors/competitors_tools/persistence_tools.py
tsmd/tools/distance.py
tsmd/tools/metric.py
tsmd/tools/neighborhood.py
tsmd/tools/plotting.py
tsmd/tools/post_processing.py
tsmd/tools/synthetic_signal.py
tsmd/tools/threshold.py
tsmd/tools/utils.py
tsmd-0.1.4.dist-info/licenses/LICENSE
tsmd-0.1.4.dist-info/METADATA
tsmd-0.1.4.dist-info/WHEEL
tsmd-0.1.4.dist-info/top_level.txt
tsmd-0.1.4.dist-info/RECORD
