Metadata-Version: 2.4
Name: tsmd
Version: 0.1.4
Summary: The TSMD project brings together Motif Discovery methods for Time Series, aiming to compare their performance through well-defined research questions and to simplify their practical use. It provides both guidelines for selecting the most suitable methods based on the data, and accessible implementations of the most relevant approaches.
Author-email: Valerio Guerrini <valerio.guerrini@ens-paris-saclay.fr>, Thibaut Germain <thibaut.germain@ens-paris-saclay.fr>, Charles Truong <charles.truong@ens-paris-saclay.fr>, Laurent Oudre <laurent.oudre@ens-paris-saclay.fr>, Paul Boniol <paul.boniol@inria.fr>
License-Expression: MIT
Project-URL: Homepage, https://github.com/grrvlr/TSMD
Requires-Python: >=3.10
License-File: LICENSE
Requires-Dist: numpy>=1.26.4
Requires-Dist: scipy>=1.12.0
Requires-Dist: matplotlib>=3.9.0
Requires-Dist: pandas>=2.0.3
Requires-Dist: numba>=0.61.0
Requires-Dist: joblib>=1.4.2
Requires-Dist: motiflets==0.6.5
Dynamic: license-file
